grabbygram/__init__.py
grabbygram/grabbygram.py
grabbygram-0.0.3.dist-info/LICENSE
grabbygram-0.0.3.dist-info/METADATA
grabbygram-0.0.3.dist-info/WHEEL
grabbygram-0.0.3.dist-info/entry_points.txt
grabbygram-0.0.3.dist-info/top_level.txt
grabbygram-0.0.3.dist-info/RECORD
