Metadata-Version: 2.1
Name: grabbygram
Version: 0.0.3
Summary: A Python package for downloading media from Telegram
Home-page: https://github.com/kavidu-dilhara/GrabbyGram
Author: Kavidu Dilhara
Author-email: contact@kavidudilhara.eu.org
Project-URL: Bug Reports, https://github.com/kavidu-dilhara/GrabbyGram/issues
Project-URL: Source, https://github.com/kavidu-dilhara/GrabbyGram
Keywords: Python Telegram  downloader  script  bot  API requests URL  media  chat  messages download  automation
Classifier: Programming Language :: Python :: 3
Classifier: License :: OSI Approved :: MIT License
Classifier: Operating System :: OS Independent
Requires-Python: >=3.6
License-File: LICENSE
Requires-Dist: telethon
Requires-Dist: tqdm
Requires-Dist: python-dotenv
Requires-Dist: pyfiglet
